exdyn/__init__.py
exdyn/commons.py
exdyn/condiff.py
exdyn/dataset.py
exdyn/funcs.py
exdyn/jac_fluct.py
exdyn/modules.py
exdyn/utils.py
exdyn/visualization.py
exdyn/workflow.py
exdyn-0.0.2.dist-info/LICENSE
exdyn-0.0.2.dist-info/METADATA
exdyn-0.0.2.dist-info/WHEEL
exdyn-0.0.2.dist-info/top_level.txt
exdyn-0.0.2.dist-info/RECORD
